commandparser
