Metadata-Version: 1.0
Name: CommandParser
Version: 0.1.2
Summary: change objects to OptionParser instances via reflection
Home-page: http://k0s.org/hg/CommandParser
Author: Jeff Hammel
Author-email: jhammel@mozilla.com
License: UNKNOWN
Platform: UNKNOWN
